hellodddd/__init__.py
hellodddd/mod1.py
hellodddd-2.32.8.dist-info/METADATA
hellodddd-2.32.8.dist-info/WHEEL
hellodddd-2.32.8.dist-info/top_level.txt
hellodddd-2.32.8.dist-info/RECORD
