Metadata-Version: 2.1
Name: hellodddd
Version: 2.32.8
Summary: This is a new library
Author: New User
